<toc version="2.0">
  <tocitem target="tasks-topic-group" text="Tareas de la Consola de Administraci&#243;n de GlassFish Server" expand="false">
    <tocitem target="task-group-jdbc" text="Conexi&#243;n de Aplicaciones a Bases de Datos mediante la Tecnolog&#237;a JDBC" expand="false">
      <tocitem target="task-setdbaccess" text="Configurar el Acceso a la Base de Datos" expand="false"></tocitem>
      <tocitem target="task-integratejdbcdriver" text="Integrar un Controlador JDBC" expand="false"></tocitem>
      <tocitem target="task-jdbcresourcenew" text="Crear un Recurso JDBC" expand="false"></tocitem>
      <tocitem target="task-jdbcresourcesedit" text="Editar un Recurso JDBC" expand="false"></tocitem>
      <tocitem target="task-jdbcresourcetargets" text="Para editar destinos de recurso JDBC" expand="false"></tocitem>
      <tocitem target="task-jdbcresourcesdelete" text="Suprimir un Recurso JDBC" expand="false"></tocitem>
      <tocitem target="task-jdbcconnectionpoolnew" text="Crear un Pool de Conexiones JDBC" expand="false"></tocitem>
      <tocitem target="task-jdbcconnectionpooledit" text="Editar Configuraci&#243;n General de los Pools de Conexiones JDBC" expand="false"></tocitem>
      <tocitem target="task-jdbcconnectionpooladvance" text="Editar Atributos Avanzados de Pools de Conexiones JDBC" expand="false"></tocitem>
      <tocitem target="task-verifyconnpoolsettings" text="Verificar la Configuraci&#243;n del Pool de Conexiones" expand="false"></tocitem>
      <tocitem target="task-jdbcconnectionpoolproperty" text="Editar las Propiedades de los Pools de Conexiones JDBC" expand="false"></tocitem>
      <tocitem target="task-jdbcconnectionpooldelete" text="Suprimir un Pool de Conexiones JDBC" expand="false"></tocitem>
    </tocitem>
  </tocitem>
  <tocitem target="ref-topic-group" text="Referencia de la Consola de Administraci&#243;n de GlassFish Server" expand="false">
    <tocitem target="ref-group-resources" text="Recursos" expand="false">
      <tocitem target="ref-group-jdbc" text="JDBC" expand="false">
        <tocitem target="ref-jdbc" text="JDBC" expand="false"></tocitem>
        <tocitem target="ref-group-jdbcresources" text="Recursos JDBC" expand="false">
          <tocitem target="ref-jdbcresources" text="Recursos JDBC" expand="false"></tocitem>
          <tocitem target="ref-jdbcresourcenew" text="Nuevo Recurso JDBC" expand="false"></tocitem>
          <tocitem target="ref-jdbcresourceedit" text="Editar Recurso JDBC" expand="false"></tocitem>
        </tocitem>
        <tocitem target="ref-group-jdbcconnectionpools" text="Pools de Conexiones" expand="false">
          <tocitem target="ref-jdbcconnectionpools" text="Pools de Conexiones" expand="false"></tocitem>
          <tocitem target="ref-jdbcconnectionpoolnew1" text="Nuevo Pool de Conexiones JDBC (Paso 1 de 2)" expand="false"></tocitem>
          <tocitem target="ref-jdbcconnectionpoolnew2" text="Nuevo Pool de Conexiones JDBC (Paso 2 de 2)" expand="false"></tocitem>
          <tocitem target="ref-jdbcconnectionpooledittab" text="Editar Pool de Conexiones" expand="false"></tocitem>
          <tocitem target="ref-jdbcconnpooladvanceattrtab" text="Editar Atributos Avanzados de Pools de Conexiones" expand="false"></tocitem>
          <tocitem target="ref-jdbcconnpoolproptab" text="Editar Propiedades de Pools de Conexiones" expand="false"></tocitem>
          <tocitem target="ref-jdbc-properties" text="Propiedades Espec&#237;ficas de Pools de Conexiones JDBC" expand="false"></tocitem>
        </tocitem>
      </tocitem>
    </tocitem>
  </tocitem>
</toc>
