<toc version="2.0">

 <tocitem target="tasks-topic-group" text="Tareas de la Consola de administraci&#243;n de GlassFish Server" expand="false">
    <tocitem target="task-group-jdbc" text="Conexi&#243;n de aplicaciones a bases de datos mediante la tecnolog&#237;a JDBC" expand="false">
        <tocitem target="task-setdbaccess" text="Para configurar el acceso a la base de datos" expand="false"></tocitem>
        <tocitem target="task-integratejdbcdriver" text="Para integrar un controlador JDBC" expand="false"></tocitem>
        <tocitem target="task-jdbcresourcenew" text="Para crear un recurso JDBC" expand="false"></tocitem>
        <tocitem target="task-jdbcresourcesedit" text="Para editar un recurso JDBC" expand="false"></tocitem>
        <tocitem target="task-jdbcresourcetargets" text="Para editar destinos de recurso JDBC" expand="false"></tocitem>
        <tocitem target="task-jdbcresourcesdelete" text="Para eliminar un recurso JDBC" expand="false"></tocitem>
        <tocitem target="task-jdbcconnectionpoolnew" text="Para crear un conjunto de conexiones JDBC" expand="false"></tocitem>
        <tocitem target="task-jdbcconnectionpooledit" text="Para editar la configuraci&#243;n general del conjunto de conexiones JDBC" expand="false"></tocitem>
        <tocitem target="task-jdbcconnectionpooladvance" text="Para editar atributos avanzados del conjunto de conexiones JDBC" expand="false"></tocitem>
        <tocitem target="task-verifyconnpoolsettings" text="Para verificar la configuraci&#243;n del conjunto de conexiones" expand="false"></tocitem>
        <tocitem target="task-jdbcconnectionpoolproperty" text="Para editar las propiedades del conjunto de conexiones JDBC" expand="false"></tocitem>
        <tocitem target="task-jdbcconnectionpooldelete" text="Para eliminar un conjunto de conexiones JDBC" expand="false"></tocitem></tocitem></tocitem>
 <tocitem target="ref-topic-group" text="Referencia de la Consola de administraci&#243;n de GlassFish Server" expand="false">
    <tocitem target="ref-group-resources" text="Recursos" expand="false">
        <tocitem target="ref-group-jdbc" text="JDBC" expand="false">
            <tocitem target="ref-jdbc" text="JDBC" expand="false"></tocitem>
            <tocitem target="ref-group-jdbcresources" text="Recursos JDBC" expand="false">
                <tocitem target="ref-jdbcresources" text="Recursos JDBC" expand="false"></tocitem>
                <tocitem target="ref-jdbcresourcenew" text="Nuevo recurso JDBC" expand="false"></tocitem>
                <tocitem target="ref-jdbcresourceedit" text="Editar recurso JDBC" expand="false"></tocitem></tocitem>
            <tocitem target="ref-group-jdbcconnectionpools" text="Conjuntos de conexiones" expand="false">
                <tocitem target="ref-jdbcconnectionpools" text="Conjuntos de conexiones" expand="false"></tocitem>
                <tocitem target="ref-jdbcconnectionpoolnew1" text="Nuevo conjunto de conexiones JDBC (Paso 1 de 2)" expand="false"></tocitem>
                <tocitem target="ref-jdbcconnectionpoolnew2" text="Nuevo conjunto de conexiones JDBC (Paso 2 de 2)" expand="false"></tocitem>
                <tocitem target="ref-jdbcconnectionpooledittab" text="Editar conjunto de conexiones" expand="false"></tocitem>
                <tocitem target="ref-jdbcconnpooladvanceattrtab" text="Editar atributos avanzados del conjunto de conexiones" expand="false"></tocitem>
                <tocitem target="ref-jdbcconnpoolproptab" text="Editar propiedades de conjunto de conexiones" expand="false"></tocitem>
                <tocitem target="ref-jdbc-properties" text="Propiedades espec&#237;ficas de los conjuntos de conexiones JDBC" expand="false"></tocitem>
</tocitem>
</tocitem>
</tocitem>
</tocitem>
</toc>
